sqller/__init__.py
sqller/exceptions.py
sqller/metaclasses.py
sqller/utils.py
sqller-1.4.1.dist-info/LICENSE.md
sqller-1.4.1.dist-info/METADATA
sqller-1.4.1.dist-info/WHEEL
sqller-1.4.1.dist-info/top_level.txt
sqller-1.4.1.dist-info/RECORD
